lazy_runtime_typechecker/__init__.py
lazy_runtime_typechecker/typechecker.py
lazy_runtime_typechecker/typechecker_errors.py
tests/__init__.py
tests/test_typechecker.py
lazy_runtime_typechecker-0.0.3.dist-info/LICENSE
lazy_runtime_typechecker-0.0.3.dist-info/METADATA
lazy_runtime_typechecker-0.0.3.dist-info/WHEEL
lazy_runtime_typechecker-0.0.3.dist-info/top_level.txt
lazy_runtime_typechecker-0.0.3.dist-info/RECORD
