Metadata-Version: 2.1
Name: lazy-runtime-typechecker
Version: 0.0.3
Summary: Simple runtime typechecker
Home-page: https://github.com/lzMeMod/runtime-typechecker
Keywords: typing,runtime,typechecker
Classifier: License :: OSI Approved :: MIT License
Classifier: Intended Audience :: Developers
Classifier: Programming Language :: Python :: 3.6
Classifier: Programming Language :: Python :: 3.7
Classifier: Programming Language :: Python :: 3.8
Classifier: Programming Language :: Python :: 3.9
Classifier: Programming Language :: Python :: 3.10
License-File: LICENSE
